linehaul/__init__.py
linehaul/logging.py
linehaul/py.typed
linehaul/events/__init__.py
linehaul/events/parser.py
linehaul/ua/__init__.py
linehaul/ua/datastructures.py
linehaul/ua/impl.py
linehaul/ua/parser.py
tests/__init__.py
tests/strategies.py
tests/test_strategies.py
tests/unit/__init__.py
tests/unit/events/__init__.py
tests/unit/events/test_parser.py
tests/unit/ua/__init__.py
tests/unit/ua/test_impl.py
tests/unit/ua/test_parser.py
linehaul-1.0.2.dist-info/LICENSE
linehaul-1.0.2.dist-info/METADATA
linehaul-1.0.2.dist-info/WHEEL
linehaul-1.0.2.dist-info/top_level.txt
linehaul-1.0.2.dist-info/RECORD
