Metadata-Version: 2.1
Name: linehaul
Version: 1.0.2
Summary: User-Agent parsing for PyPI analytics
Author-email: PyPI Admins <admin@pypi.org>
Project-URL: Homepage, https://github.com/pypi/linehaul-cloud-function
Project-URL: Source, https://github.com/pypi/linehaul-cloud-function
Keywords: pypi,user-agent,parsing
Classifier: Development Status :: 5 - Production/Stable
Classifier: Intended Audience :: Developers
Classifier: License :: OSI Approved :: Apache Software License
Classifier: Programming Language :: Python :: 3
Classifier: Programming Language :: Python :: 3.11
Classifier: Programming Language :: Python :: 3 :: Only
Classifier: Typing :: Typed
Requires-Python: <4,>=3.11
License-File: LICENSE
Requires-Dist: cattrs
Requires-Dist: packaging
Requires-Dist: pyparsing
